dexplo/__init__.py
dexplo/_date.py
dexplo/_date_funcs.py
dexplo/_frame.py
dexplo/_groupby.py
dexplo/_math_columns.py
dexplo/_stat_funcs.py
dexplo/_strings.py
dexplo/_utils.py
dexplo/options.py
dexplo/testing.py
dexplo/_libs/__init__.py
dexplo/_libs/_date.cpython-36m-darwin.so
dexplo/_libs/count_sort.cpython-36m-darwin.so
dexplo/_libs/date.cpython-36m-darwin.so
dexplo/_libs/groupby.cpython-36m-darwin.so
dexplo/_libs/math.cpython-36m-darwin.so
dexplo/_libs/sort_rank.cpython-36m-darwin.so
dexplo/_libs/string_funcs.cpython-36m-darwin.so
dexplo/_libs/timedelta.cpython-36m-darwin.so
dexplo/_libs/unique.cpython-36m-darwin.so
dexplo/_libs/validate_arrays.cpython-36m-darwin.so
dexplo/tests/__init__.py
dexplo/tests/test_frame.py
dexplo/tests/test_misc_df_funcs.py
dexplo/tests/test_missing.py
dexplo/tests/test_stat_funcs.py
dexplo-0.0.13.dist-info/DESCRIPTION.rst
dexplo-0.0.13.dist-info/METADATA
dexplo-0.0.13.dist-info/RECORD
dexplo-0.0.13.dist-info/WHEEL
dexplo-0.0.13.dist-info/metadata.json
dexplo-0.0.13.dist-info/top_level.txt
