Metadata-Version: 2.0
Name: dexplo
Version: 0.0.13
Summary: A library for data exploration comparible to pandas. No Series, No hierarchical indexing, only one indexer [ ]
Home-page: https://github.com/dexplo/dexplo
Author: Ted Petrou
Author-email: petrou.theodore@gmail.com
License: BSD 3-clause
Keywords: data analysis exploration aggregation pandas numpy
Platform: UNKNOWN
Classifier: Development Status :: 3 - Alpha
Classifier: Intended Audience :: Science/Research
Classifier: Topic :: Scientific/Engineering
Classifier: License :: OSI Approved :: BSD License
Classifier: Programming Language :: Python :: 3.6
Requires-Python: >=3.6
Requires-Dist: numpy
